intx/__init__.py
intx/intx.py
Intx-0.0.2.dist-info/METADATA
Intx-0.0.2.dist-info/WHEEL
Intx-0.0.2.dist-info/top_level.txt
Intx-0.0.2.dist-info/RECORD
