Metadata-Version: 2.1
Name: Intx
Version: 0.0.2
Summary: An extension to the base type int with some handy functions
Home-page: https://github.com/SH4D0WKING/Intx
Author: Lars Van Cauter
Author-email: larsvancauter@gmail.com
License: UNKNOWN
Platform: UNKNOWN
Classifier: Programming Language :: Python :: 3
Classifier: License :: OSI Approved :: MIT License
Classifier: Operating System :: OS Independent
Requires-Python: >=3.6
